AaditsHangman/__init__.py
AaditsHangman-0.0.4.dist-info/LICENSE
AaditsHangman-0.0.4.dist-info/METADATA
AaditsHangman-0.0.4.dist-info/WHEEL
AaditsHangman-0.0.4.dist-info/top_level.txt
AaditsHangman-0.0.4.dist-info/RECORD
