Metadata-Version: 2.1
Name: AaditsHangman
Version: 0.0.4
Summary: A hangman game created on tkinter python
Home-page: https://github.com/aaditisawesome/hangman
Author: Aadit Bansal
Author-email: aaditisawesome@gmail.com
License: UNKNOWN
Platform: UNKNOWN
Classifier: Programming Language :: Python :: 3
Classifier: License :: OSI Approved :: Apache Software License
Classifier: Operating System :: OS Independent
Requires-Python: >=3.6
Requires-Dist: RandomWords
